memobase/__init__.py
memobase/error.py
memobase/network.py
memobase/utils.py
memobase/core/__init__.py
memobase/core/async_entry.py
memobase/core/blob.py
memobase/core/entry.py
memobase/core/type.py
memobase/core/user.py
memobase/patch/__init__.py
memobase/patch/openai.py
chat_memobase-1.0.6.dist-info/LICENSE
chat_memobase-1.0.6.dist-info/METADATA
chat_memobase-1.0.6.dist-info/WHEEL
chat_memobase-1.0.6.dist-info/top_level.txt
chat_memobase-1.0.6.dist-info/RECORD
