Metadata-Version: 2.1
Name: chat_memobase
Version: 1.0.6
Summary: Client library of memory based on Memobase: manage user memory for my LLM applications
Author: Allison
License: Apache license 2.0
Classifier: Programming Language :: Python :: 3
Classifier: Programming Language :: Python :: 3.11
Classifier: Programming Language :: Python :: 3.12
Classifier: Operating System :: OS Independent
Requires-Python: >=3.11
License-File: LICENSE
